gpt_cli/__init__.py
gpt_cli/cli.py
gpt_cli/config.py
tests/__init__.py
tests/test_cli.py
gpt_4o_cli-0.1.4.dist-info/METADATA
gpt_4o_cli-0.1.4.dist-info/WHEEL
gpt_4o_cli-0.1.4.dist-info/entry_points.txt
gpt_4o_cli-0.1.4.dist-info/top_level.txt
gpt_4o_cli-0.1.4.dist-info/RECORD
