Metadata-Version: 2.1
Name: gpt-4o-cli
Version: 0.1.4
Summary: A CLI application to interact with OpenAI's GPT models
Home-page: https://github.com/invinciblerd/gpt_cli
Author: Dipendra Kumar Shah
Author-email: dipendrashah0789878@gmail.com
Classifier: Programming Language :: Python :: 3
Classifier: License :: OSI Approved :: MIT License
Classifier: Operating System :: OS Independent
Requires-Python: >=3.6
Requires-Dist: openai
Requires-Dist: httpx
